nonebot_plugin_hacker_news/__init__.py
nonebot_plugin_hacker_news/broadcaster.py
nonebot_plugin_hacker_news/config.py
nonebot_plugin_hacker_news/data_source.py
nonebot_plugin_hacker_news-0.1.3.dist-info/licenses/LICENSE
nonebot_plugin_hacker_news-0.1.3.dist-info/METADATA
nonebot_plugin_hacker_news-0.1.3.dist-info/WHEEL
nonebot_plugin_hacker_news-0.1.3.dist-info/entry_points.txt
nonebot_plugin_hacker_news-0.1.3.dist-info/top_level.txt
nonebot_plugin_hacker_news-0.1.3.dist-info/RECORD
