Metadata-Version: 2.4
Name: nonebot-plugin-hacker-news
Version: 0.1.3
Summary: NoneBot2插件 - 获取Hacker News文章并进行播报
Author-email: perfsakuya <blujewel350@gmail.com>
License-Expression: MIT
Project-URL: Repository, https://github.com/perfsakuya/nonebot-plugin-hacker-news
Classifier: Development Status :: 4 - Beta
Classifier: Framework :: Robot Framework
Classifier: Programming Language :: Python :: 3.9
Requires-Python: >=3.9
License-File: LICENSE
Requires-Dist: nonebot2>=2.3.0
Requires-Dist: nonebot-adapter-onebot>=2.2.1
Requires-Dist: nonebot-plugin-apscheduler>=0.2.0
Requires-Dist: httpx>=0.24.0
Dynamic: license-file
